{
  "info": {
    "name": "Maximus API Collection",
    "description": "Complete API collection for Maximus Backend",
    "schema": "https://schema.getpostman.com/json/collection/v2.1.0/collection.json"
  },
  "item": [
    {
      "name": "Authentication",
      "description": "Auth related endpoints",
      "item": [
        {
          "name": "Register User",
          "request": {
            "method": "POST",
            "header": [
              {
                "key": "Content-Type",
                "value": "application/json"
              }
            ],
            "body": {
              "mode": "raw",
              "raw": "{\n    \"name\": \"Test User\",\n    \"email\": \"testuser@example.com\",\n    \"password\": \"Password123!\",\n    \"phoneNumber\": \"+919876543210\"\n}"
            },
            "url": {
              "raw": "{{baseUrl}}/api/auth/register",
              "host": ["{{baseUrl}}"],
              "path": ["api", "auth", "register"]
            },
            "description": "Register a new user account"
          }
        },
        {
          "name": "Login",
          "request": {
            "method": "POST",
            "header": [
              {
                "key": "Content-Type",
                "value": "application/json"
              }
            ],
            "body": {
              "mode": "raw",
              "raw": "{\n    \"email\": \"testuser@example.com\",\n    \"password\": \"Password123!\"\n}"
            },
            "url": {
              "raw": "{{baseUrl}}/api/auth/login",
              "host": ["{{baseUrl}}"],
              "path": ["api", "auth", "login"]
            },
            "description": "Authenticate user and get JWT token"
          }
        },
        {
          "name": "Google Login",
          "request": {
            "method": "POST",
            "header": [
              {
                "key": "Content-Type",
                "value": "application/json"
              }
            ],
            "body": {
              "mode": "raw",
              "raw": "{\n    \"credential\": \"GOOGLE_ID_TOKEN\"\n}"
            },
            "url": {
              "raw": "{{baseUrl}}/api/auth/google-login",
              "host": ["{{baseUrl}}"],
              "path": ["api", "auth", "google-login"]
            },
            "description": "Login with Google OAuth credential"
          }
        },
        {
          "name": "Forgot Password",
          "request": {
            "method": "POST",
            "header": [
              {
                "key": "Content-Type",
                "value": "application/json"
              }
            ],
            "body": {
              "mode": "raw",
              "raw": "{\n    \"email\": \"testuser@example.com\"\n}"
            },
            "url": {
              "raw": "{{baseUrl}}/api/auth/forgot-password",
              "host": ["{{baseUrl}}"],
              "path": ["api", "auth", "forgot-password"]
            },
            "description": "Request password reset email"
          }
        },
        {
          "name": "Reset Password",
          "request": {
            "method": "POST",
            "header": [
              {
                "key": "Content-Type",
                "value": "application/json"
              }
            ],
            "body": {
              "mode": "raw",
              "raw": "{\n    \"token\": \"RESET_TOKEN\",\n    \"password\": \"NewPassword123!\"\n}"
            },
            "url": {
              "raw": "{{baseUrl}}/api/auth/reset-password",
              "host": ["{{baseUrl}}"],
              "path": ["api", "auth", "reset-password"]
            },
            "description": "Reset password with token from email"
          }
        },
        {
          "name": "Request OTP",
          "request": {
            "method": "POST",
            "header": [
              {
                "key": "Content-Type",
                "value": "application/json"
              }
            ],
            "body": {
              "mode": "raw",
              "raw": "{\n    \"phoneNumber\": \"+919876543210\"\n}"
            },
            "url": {
              "raw": "{{baseUrl}}/api/auth/request-otp",
              "host": ["{{baseUrl}}"],
              "path": ["api", "auth", "request-otp"]
            },
            "description": "Request OTP for phone verification"
          }
        },
        {
          "name": "Verify OTP",
          "request": {
            "method": "POST",
            "header": [
              {
                "key": "Content-Type",
                "value": "application/json"
              }
            ],
            "body": {
              "mode": "raw",
              "raw": "{\n    \"phoneNumber\": \"+919876543210\",\n    \"otp\": \"123456\"\n}"
            },
            "url": {
              "raw": "{{baseUrl}}/api/auth/verify-otp",
              "host": ["{{baseUrl}}"],
              "path": ["api", "auth", "verify-otp"]
            },
            "description": "Verify OTP code sent to phone"
          }
        },
        {
          "name": "Get Profile",
          "request": {
            "method": "GET",
            "header": [
              {
                "key": "Authorization",
                "value": "Bearer {{authToken}}"
              }
            ],
            "url": {
              "raw": "{{baseUrl}}/api/auth/profile",
              "host": ["{{baseUrl}}"],
              "path": ["api", "auth", "profile"]
            },
            "description": "Get current user profile"
          }
        },
        {
          "name": "Update Profile",
          "request": {
            "method": "PUT",
            "header": [
              {
                "key": "Authorization",
                "value": "Bearer {{authToken}}"
              },
              {
                "key": "Content-Type",
                "value": "application/json"
              }
            ],
            "body": {
              "mode": "raw",
              "raw": "{\n    \"name\": \"Updated Name\",\n    \"phoneNumber\": \"+919876543210\"\n}"
            },
            "url": {
              "raw": "{{baseUrl}}/api/auth/profile",
              "host": ["{{baseUrl}}"],
              "path": ["api", "auth", "profile"]
            },
            "description": "Update user profile information"
          }
        },
        {
          "name": "Submit KYC Update Request",
          "request": {
            "method": "POST",
            "header": [
              {
                "key": "Authorization",
                "value": "Bearer {{authToken}}"
              },
              {
                "key": "Content-Type",
                "value": "application/json"
              }
            ],
            "body": {
              "mode": "raw",
              "raw": "{\n    \"bankAccount\": {\n        \"accountNumber\": \"1234567890\",\n        \"ifscCode\": \"HDFC0001234\",\n        \"accountHolderName\": \"Test User\"\n    },\n    \"kycInformation\": {\n        \"aadhaarNumber\": \"123456789012\",\n        \"panNumber\": \"ABCDE1234F\"\n    }\n}"
            },
            "url": {
              "raw": "{{baseUrl}}/api/auth/kyc/update-request",
              "host": ["{{baseUrl}}"],
              "path": ["api", "auth", "kyc", "update-request"]
            },
            "description": "Submit a request to update KYC information"
          }
        }
      ]
    }
  ]
}
